{"activities": [{"kind": "admin#reports#activity", "id": {"time": "2022-08-02T07:09:00.429Z", "uniqueQualifier": "-6303014327256218067", "applicationName": "user_accounts", "customerId": "C00mpaiwz"}, "etag": "\"_ZVRqe-BUDYcYeOIPo-gm6Eh1QaGne4ACjHHI6qsr6A/gyx-nOcYjq3Rj2fWq5GYhiZBsL0\"", "actor": {"callerType": "USER", "email": "workspace@cloud-response.com", "profileId": "102509620547980436027"}, "ipAddress": "31.171.152.13", "events": [{"type": "email_forwarding_change", "name": "email_forwarding_out_of_domain", "parameters": [{"name": "email_forwarding_destination_address", "value": "korstiaanstam@gmail.com"}]}]}, {"kind": "admin#reports#activity", "id": {"time": "2022-08-02T07:08:03.018Z", "uniqueQualifier": "8958327431473786420", "applicationName": "user_accounts", "customerId": "C00mpaiwz"}, "etag": "\"_ZVRqe-BUDYcYeOIPo-gm6Eh1QaGne4ACjHHI6qsr6A/A59hRE9Oahn4bdGbzJBSjfYeZfc\"", "actor": {"callerType": "USER", "email": "workspace@cloud-response.com", "profileId": "102509620547980436027"}, "ipAddress": "31.171.152.13", "events": [{"type": "2sv_change", "name": "2sv_enroll"}]}, {"kind": "admin#reports#activity", "id": {"time": "2022-07-27T09:31:51.473Z", "uniqueQualifier": "6900318258760211314", "applicationName": "user_accounts", "customerId": "C00mpaiwz"}, "etag": "\"_ZVRqe-BUDYcYeOIPo-gm6Eh1QaGne4ACjHHI6qsr6A/a56miez47Ug1ByjAdzcLiAv_GlM\"", "actor": {"callerType": "USER", "email": "workspace@cloud-response.com", "profileId": "102509620547980436027"}, "ipAddress": "80.114.222.200", "events": [{"type": "email_forwarding_change", "name": "email_forwarding_out_of_domain", "parameters": [{"name": "email_forwarding_destination_address", "value": "sleneguthu@memsg.site"}]}]}, {"kind": "admin#reports#activity", "id": {"time": "2022-07-27T09:31:13.944Z", "uniqueQualifier": "-2121597430569433497", "applicationName": "user_accounts", "customerId": "C00mpaiwz"}, "etag": "\"_ZVRqe-BUDYcYeOIPo-gm6Eh1QaGne4ACjHHI6qsr6A/lLvwTotLIgo_8DLmj3yslwlm7jo\"", "actor": {"callerType": "USER", "email": "workspace@cloud-response.com", "profileId": "102509620547980436027"}, "ipAddress": "80.114.222.200", "events": [{"type": "email_forwarding_change", "name": "email_forwarding_out_of_domain", "parameters": [{"name": "email_forwarding_destination_address", "value": "apt1337@throwawaymail.com"}]}]}, {"kind": "admin#reports#activity", "id": {"time": "2022-07-21T13:40:49.268Z", "uniqueQualifier": "-6977913962455696939", "applicationName": "user_accounts", "customerId": "C00mpaiwz"}, "etag": "\"_ZVRqe-BUDYcYeOIPo-gm6Eh1QaGne4ACjHHI6qsr6A/KNpRbIeqKJRteuQ7gcPLjNg67qA\"", "actor": {"callerType": "USER", "email": "suspicious@cloud-response.com", "profileId": "102509620547980436027"}, "ipAddress": "80.114.222.200", "events": [{"type": "password_change", "name": "password_edit"}]}, {"kind": "admin#reports#activity", "id": {"time": "2022-03-14T20:36:35.143Z", "uniqueQualifier": "-5188215030825995109", "applicationName": "user_accounts", "customerId": "C00mpaiwz"}, "etag": "\"_ZVRqe-BUDYcYeOIPo-gm6Eh1QaGne4ACjHHI6qsr6A/uhXcfwp1i17pJOm69f0jKbVIj18\"", "actor": {"callerType": "USER", "email": "greg@cloud-response.com", "profileId": "103761500014234497706"}, "ipAddress": "2.2.2.2", "events": [{"type": "password_change", "name": "password_edit"}]}]}